Metadata-Version: 2.1
Name: declutter
Version: 0.1
Summary: A commandline utility to declutter the files in current directory by organizing into folders automatically.
Home-page: https://github.com/xKynn/declutter
Author: xKynn
Author-email: xKynn@github.com
License: UNKNOWN
Platform: UNKNOWN
Classifier: License :: OSI Approved :: MIT License
Classifier: Operating System :: OS Independent
